promptist/__init__.py
promptist/models.py
promptist/renderer.py
promptist-0.1.3.dist-info/LICENSE
promptist-0.1.3.dist-info/METADATA
promptist-0.1.3.dist-info/WHEEL
promptist-0.1.3.dist-info/top_level.txt
promptist-0.1.3.dist-info/RECORD
