Metadata-Version: 2.1
Name: promptist
Version: 0.1.3
Summary: Short description of your package
Home-page: https://github.com/otanadzetsotne/promptist
Author: Tsotne Otanadze
Author-email: otanadzetsotne@yahoo.com
Classifier: Programming Language :: Python :: 3
Classifier: License :: OSI Approved :: MIT License
Classifier: Operating System :: OS Independent
Requires-Python: >=3.10
License-File: LICENSE
Requires-Dist: annotated-types ==0.7.0
Requires-Dist: pydantic ==2.9.0
Requires-Dist: pydantic-core ==2.23.2
Requires-Dist: typing-extensions ==4.12.2
Requires-Dist: tzdata ==2024.1
